ticsummary_sodib/__init__.py
ticsummary_sodib/__main__.py
ticsummary_sodib/backWorking.py
ticsummary_sodib/callibrationGalo.py
ticsummary_sodib/dataTIC.py
ticsummary_sodib/dataWriter.py
ticsummary_sodib/handlerData.py
ticsummary_sodib/inputDataHandler.py
ticsummary_sodib/modeShowData.py
ticsummary_sodib/model.py
ticsummary_sodib/mysql.py
ticsummary_sodib/readerCSV.py
ticsummary_sodib/readerFiles.py
ticsummary_sodib/resources/__init__.py
ticsummary_sodib/resources/images/__init__.py
ticsummary_sodib/ui/__init__.py
ticsummary_sodib/ui/dialogCalibrationGalo.py
ticsummary_sodib/ui/galoBeam.py
ticsummary_sodib/ui/mainWindow.py
ticsummary_sodib/ui/profileBeamDock.py
ticsummary_sodib/ui/serverParametersDialog.py
ticsummary_sodib/ui/settingsColorBarDialog.py
ticsummary_sodib/ui/viewGraphicsDialog.py
ticsummary_sodib/ui/uic/__init__.py
ticsummary_sodib/ui/uic/connectServer.ui
ticsummary_sodib/ui/uic/dialogCalibrationGalo.ui
ticsummary_sodib/ui/uic/mainWindow.ui
ticsummary_sodib/ui/uic/settingsColorBarDialog.ui
ticsummary_sodib/ui/uic/viewGraphics.ui
neofti_ticsummary_sodib-0.0.5.dist-info/METADATA
neofti_ticsummary_sodib-0.0.5.dist-info/WHEEL
neofti_ticsummary_sodib-0.0.5.dist-info/entry_points.txt
neofti_ticsummary_sodib-0.0.5.dist-info/top_level.txt
neofti_ticsummary_sodib-0.0.5.dist-info/RECORD
